pyswip/__init__.py
pyswip/core.py
pyswip/easy.py
pyswip/prolog.py
pyswip-0.3.0.dist-info/LICENSE
pyswip-0.3.0.dist-info/METADATA
pyswip-0.3.0.dist-info/WHEEL
pyswip-0.3.0.dist-info/top_level.txt
pyswip-0.3.0.dist-info/RECORD
