Metadata-Version: 2.1
Name: pyswip
Version: 0.3.0
Summary: PySwip enables querying SWI-Prolog in your Python programs.
Author-email: Yuce Tekol <yucetekol@gmail.com>
Project-URL: Download, https://github.com/yuce/pyswip/releases
Project-URL: Homepage, https://github.com/yuce/pyswip
Keywords: ai,artificial intelligence,ctypes,ffi,prolog
Classifier: Development Status :: 3 - Alpha
Classifier: Intended Audience :: Developers
Classifier: Intended Audience :: Science/Research
Classifier: License :: OSI Approved :: MIT License
Classifier: Operating System :: OS Independent
Classifier: Programming Language :: Python
Classifier: Topic :: Scientific/Engineering :: Artificial Intelligence
Classifier: Topic :: Software Development :: Libraries :: Python Modules
Classifier: Programming Language :: Python :: 3.8
Classifier: Programming Language :: Python :: 3.9
Classifier: Programming Language :: Python :: 3.10
Classifier: Programming Language :: Python :: 3.11
Classifier: Programming Language :: Python :: 3.12
Classifier: Programming Language :: Python :: Implementation :: CPython
Requires-Python: >=3.8
License-File: LICENSE
